Metadata-Version: 2.1
Name: retico-googleasr
Version: 0.1.5
Summary: The GoogleASR incremental module for the retico framework
Home-page: https://github.com/retico-team/retico-googleasr
Download-URL: https://github.com/retico-team/retico-googleasr
Author: Thilo Michael
Author-email: uhlomuhlo@gmail.com
Keywords: retico,framework,incremental,dialogue,dialog,asr,speech
Classifier: Development Status :: 2 - Pre-Alpha
Classifier: Programming Language :: Python :: 3
Classifier: License :: OSI Approved :: Apache Software License
Requires-Python: >=3.6, <4
License-File: LICENSE
